<annotation>
	<folder>img</folder>
	<filename>cards-[H6]-001.jpg</filename>
	<path>/home/eddie/study/blackjack/data/playing-cards/img/cards-[H6]-001.jpg</path>
	<source>
		<database>Unknown</database>
	</source>
	<size>
		<width>4128</width>
		<height>2322</height>
		<depth>3</depth>
	</size>
	<segmented>0</segmented>
	<object>
		<name>6h</name>
		<pose>Unspecified</pose>
		<truncated>0</truncated>
		<difficult>0</difficult>
		<bndbox>
			<xmin>1402</xmin>
			<ymin>1287</ymin>
			<xmax>1710</xmax>
			<ymax>1415</ymax>
		</bndbox>
	</object>
	<object>
		<name>6h</name>
		<pose>Unspecified</pose>
		<truncated>0</truncated>
		<difficult>0</difficult>
		<bndbox>
			<xmin>2474</xmin>
			<ymin>559</ymin>
			<xmax>2782</xmax>
			<ymax>679</ymax>
		</bndbox>
	</object>
</annotation>
